CHANGES.txt
CONTRIBUTORS.txt
README.txt
bootstrap.py
buildout.cfg
setup.py
collective/__init__.py
collective.recipe.minify.egg-info/PKG-INFO
collective.recipe.minify.egg-info/SOURCES.txt
collective.recipe.minify.egg-info/dependency_links.txt
collective.recipe.minify.egg-info/entry_points.txt
collective.recipe.minify.egg-info/namespace_packages.txt
collective.recipe.minify.egg-info/not-zip-safe
collective.recipe.minify.egg-info/requires.txt
collective.recipe.minify.egg-info/top_level.txt
collective/recipe/__init__.py
collective/recipe/minify/README.txt
collective/recipe/minify/__init__.py
collective/recipe/minify/runner.py
collective/recipe/minify/tests/__init__.py
collective/recipe/minify/tests/test_docs.py
collective/recipe/minify/tests/test_runner.py
collective/recipe/minify/tests/sample/README.txt
collective/recipe/minify/tests/sample/another.js
collective/recipe/minify/tests/sample/resources/scripts/bar.js
collective/recipe/minify/tests/sample/resources/scripts/foo.js
collective/recipe/minify/tests/sample/resources/styles/beautiful.css
collective/recipe/minify/tests/sample/resources/styles/foo.css