Metadata-Version: 1.0
Name: collective.recipe.minify
Version: 1.0
Summary: A minify-wrapper for CSS & JavaScript resources
Home-page: http://pypi.python.org/collective.recipe.minify
Author: Tom Gross
Author-email: itconsense@gmail.com
License: ZPL
Keywords: CSS JavaScript Minify Performance
Platform: UNKNOWN
Classifier: Framework :: Buildout
Classifier: Intended Audience :: Developers
Classifier: Topic :: Software Development :: Build Tools
Classifier: License :: OSI Approved :: Zope Public License
